codcat/__init__.py
codcat/cli.py
codcat/downloader.py
codcat/manifest.yaml
codcat/pyg.py
codcat/tok.py
codcat/models/__init__.py
codcat/models/estimator.py
codcat/utils/__init__.py
codcat/utils/dataset.py
codcat/utils/tokenization.py
codcat/utils/types.py
codcat-0.2.0.dist-info/LICENSE
codcat-0.2.0.dist-info/METADATA
codcat-0.2.0.dist-info/WHEEL
codcat-0.2.0.dist-info/top_level.txt
codcat-0.2.0.dist-info/RECORD
