Metadata-Version: 2.1
Name: codcat
Version: 0.2.0
Summary: Code snippets language classification tool
Author-email: Konstantin Templin <1qnbhd@gmail.com>
Maintainer-email: Konstantin Templin <1qnbhd@gmail.com>
License: MIT
Project-URL: Repository, https://gitlab.com/codcat/codcat
Keywords: code,snippets,classification,language,NLP,ML
Classifier: Intended Audience :: Science/Research
Classifier: Intended Audience :: Developers
Classifier: Programming Language :: Python :: 3
Classifier: Programming Language :: Python :: 3.6
Classifier: Programming Language :: Python :: 3.7
Classifier: Programming Language :: Python :: 3.8
Classifier: Programming Language :: Python :: 3.9
Classifier: Programming Language :: Python :: 3.10
Classifier: Programming Language :: Python :: 3 :: Only
Classifier: Topic :: Scientific/Engineering
Classifier: Topic :: Scientific/Engineering :: Mathematics
Classifier: Topic :: Scientific/Engineering :: Artificial Intelligence
Classifier: Topic :: Software Development
Classifier: Topic :: Software Development :: Libraries
Classifier: Topic :: Software Development :: Libraries :: Python Modules
Requires-Python: >=3.9
License-File: LICENSE
Requires-Dist: pygments
Requires-Dist: pandas
Requires-Dist: scikit-learn
Requires-Dist: numpy
Requires-Dist: onnxruntime (==1.15.0)
Requires-Dist: skl2onnx (==1.14.1)
Requires-Dist: onnxmltools (==1.11.2)
Requires-Dist: nltk (>=3.8.1)
Requires-Dist: click (>=8.1.3)
Requires-Dist: rich (>=13.3.3)
Requires-Dist: lightgbm (>=3.3.0)
Requires-Dist: pyyaml
Requires-Dist: requests
